gitq/__init__.py
gitq/continuations.py
gitq/git.py
gitq/git_queue.py
gitq/git_swap.py
gitq/py.typed
gitq/queue.py
gitq-0.0.3.dist-info/METADATA
gitq-0.0.3.dist-info/WHEEL
gitq-0.0.3.dist-info/entry_points.txt
gitq-0.0.3.dist-info/RECORD
